b2sum/__init__.py
b2sum/__main__.py
b2sum/b2sum.py
b2sum-1.0.0.dist-info/LICENSE
b2sum-1.0.0.dist-info/METADATA
b2sum-1.0.0.dist-info/WHEEL
b2sum-1.0.0.dist-info/entry_points.txt
b2sum-1.0.0.dist-info/top_level.txt
b2sum-1.0.0.dist-info/RECORD
